eagerx_tutorials/__init__.py
eagerx_tutorials/animate.py
eagerx_tutorials/helper.py
eagerx_tutorials/pendulum/__init__.py
eagerx_tutorials/pendulum/engine_nodes.py
eagerx_tutorials/pendulum/engine_states.py
eagerx_tutorials/pendulum/gym_implementation.py
eagerx_tutorials/pendulum/objects.py
eagerx_tutorials/pendulum/overlay.py
eagerx_tutorials/pendulum/pendulum_ode.py
eagerx_tutorials/pendulum/pendulum_render.py
eagerx_tutorials/pendulum/pid.py
eagerx_tutorials/pendulum/processor.py
eagerx_tutorials/pendulum/reset.py
eagerx_tutorials/quadruped/__init__.py
eagerx_tutorials/quadruped/cartesian_control.py
eagerx_tutorials/quadruped/cpg_gait.py
eagerx_tutorials/quadruped/evaluate.py
eagerx_tutorials/quadruped/go1/__init__.py
eagerx_tutorials/quadruped/go1/configs_go1.py
eagerx_tutorials/quadruped/go1/go1_description/meshes/calf.obj
eagerx_tutorials/quadruped/go1/go1_description/meshes/calf.stl
eagerx_tutorials/quadruped/go1/go1_description/meshes/hip.obj
eagerx_tutorials/quadruped/go1/go1_description/meshes/hip.stl
eagerx_tutorials/quadruped/go1/go1_description/meshes/thigh.obj
eagerx_tutorials/quadruped/go1/go1_description/meshes/thigh.stl
eagerx_tutorials/quadruped/go1/go1_description/meshes/thigh_mirror.obj
eagerx_tutorials/quadruped/go1/go1_description/meshes/thigh_mirror.stl
eagerx_tutorials/quadruped/go1/go1_description/meshes/trunk.stl
eagerx_tutorials/quadruped/go1/go1_description/urdf/go1.urdf
eagerx_tutorials/quadruped/hopf_network.py
eagerx_tutorials/quadruped/object.py
eagerx_tutorials/quadruped/overlay.py
eagerx_tutorials-0.1.35.dist-info/LICENSE
eagerx_tutorials-0.1.35.dist-info/METADATA
eagerx_tutorials-0.1.35.dist-info/WHEEL
eagerx_tutorials-0.1.35.dist-info/RECORD
