Metadata-Version: 2.1
Name: eagerx_tutorials
Version: 0.1.35
Summary: Tutorials on how to use EAGERx.
Home-page: https://github.com/eager-dev/eagerx_tutorials
License: Apache2.0
Author: Jelle Luijkx
Author-email: j.d.luijkx@tudelft.nl
Requires-Python: >=3.7,<4.0
Classifier: License :: Other/Proprietary License
Classifier: Programming Language :: Python :: 3
Classifier: Programming Language :: Python :: 3.7
Classifier: Programming Language :: Python :: 3.8
Classifier: Programming Language :: Python :: 3.9
Classifier: Programming Language :: Python :: 3.10
Classifier: Programming Language :: Python :: 3.11
Classifier: Programming Language :: Python :: 3.12
Classifier: Programming Language :: Python :: 3.13
Requires-Dist: PyVirtualDisplay (>=3.0,<4.0)
Requires-Dist: eagerx (>=0.1.38,<0.2.0)
Requires-Dist: eagerx-ode (>=0.1.26,<0.2.0)
Requires-Dist: eagerx-pybullet (>=0.1.11,<0.2.0)
Requires-Dist: ipywidgets (>=7.7.0,<8.0.0)
Requires-Dist: jupyterlab (>=3.3.4,<4.0.0)
Requires-Dist: nbconvert (>=6.5.0,<7.0.0)
Requires-Dist: shimmy (>=1.1.0,<2.0.0)
Requires-Dist: tqdm (>=4.64.0,<5.0.0)
Project-URL: Documentation, https://eagerx.readthedocs.io/en/master/
Project-URL: Repository, https://github.com/eager-dev/eagerx_tutorials
